odoo/addons/stock_putaway_by_route/README.rst
odoo/addons/stock_putaway_by_route/__init__.py
odoo/addons/stock_putaway_by_route/__manifest__.py
odoo/addons/stock_putaway_by_route/i18n/stock_putaway_by_route.pot
odoo/addons/stock_putaway_by_route/models/__init__.py
odoo/addons/stock_putaway_by_route/models/stock_location.py
odoo/addons/stock_putaway_by_route/models/stock_move.py
odoo/addons/stock_putaway_by_route/models/stock_move_line.py
odoo/addons/stock_putaway_by_route/models/stock_putaway_rule.py
odoo/addons/stock_putaway_by_route/readme/CONFIGURATION.rst
odoo/addons/stock_putaway_by_route/readme/CONTRIBUTORS.rst
odoo/addons/stock_putaway_by_route/readme/DESCRIPTION.rst
odoo/addons/stock_putaway_by_route/static/description/icon.png
odoo/addons/stock_putaway_by_route/static/description/index.html
odoo/addons/stock_putaway_by_route/tests/__init__.py
odoo/addons/stock_putaway_by_route/tests/test_route_putaway.py
odoo/addons/stock_putaway_by_route/tests/test_view.py
odoo/addons/stock_putaway_by_route/views/stock_putaway_rule_views.xml
odoo13_addon_stock_putaway_by_route-13.0.1.2.0.dist-info/METADATA
odoo13_addon_stock_putaway_by_route-13.0.1.2.0.dist-info/WHEEL
odoo13_addon_stock_putaway_by_route-13.0.1.2.0.dist-info/top_level.txt
odoo13_addon_stock_putaway_by_route-13.0.1.2.0.dist-info/RECORD
