Metadata-Version: 2.1
Name: odoo13-addon-stock-putaway-by-route
Version: 13.0.1.2.0
Summary: Add a match by route on putaway, after product and categories
Home-page: https://github.com/OCA/stock-logistics-workflow
Author: Camptocamp, Odoo Community Association (OCA)
Author-email: support@odoo-community.org
License: AGPL-3
Platform: UNKNOWN
Classifier: Programming Language :: Python
Classifier: Framework :: Odoo
Classifier: License :: OSI Approved :: GNU Affero General Public License v3
Requires-Python: >=3.5
Requires-Dist: odoo13-addon-stock-putaway-hook
Requires-Dist: odoo (<13.1dev,>=13.0a)
